LICENSE
MANIFEST.in
README.rst
requirements.txt
setup.py
seolib/__init__.py
seolib/api.py
seolib/decorators.py
seolib/errors.py
seolib/helpers.py
seolib/tests.py
seolib.egg-info/PKG-INFO
seolib.egg-info/SOURCES.txt
seolib.egg-info/dependency_links.txt
seolib.egg-info/requires.txt
seolib.egg-info/top_level.txt