Metadata-Version: 1.1
Name: seolib
Version: 0.1.3
Summary: Python lib that provides you with some usefull and simple methods to obtain website metrics
Home-page: http://www.xelblch.com/seolib/
Author: Andrey Bernatsky
Author-email: xelblch@gmail.com
License: Licensed under the Apache License, Version 2.0 (the "License");
